cfe/__init__.py
cfe/__main__.py
cfe/cli.py
cfe-0.0.22.dist-info/METADATA
cfe-0.0.22.dist-info/WHEEL
cfe-0.0.22.dist-info/entry_points.txt
cfe-0.0.22.dist-info/top_level.txt
cfe-0.0.22.dist-info/RECORD
