Metadata-Version: 2.1
Name: cfe
Version: 0.0.22
Summary: Build projects faster with cfe
Author-email: Justin Mitchel <hello@codingforentrepreneurs.com>
Project-URL: Homepage, https://github.com/codingforentrepreneurs/cfe
Keywords: cfe,build,projects,faster,codingforentrepreneurs
Classifier: Programming Language :: Python :: 3
Classifier: Operating System :: OS Independent
Requires-Python: >=3.10
Requires-Dist: requests>=2.25.1
Requires-Dist: fire
Requires-Dist: rich
